anyascii/__init__.py
anyascii/_data/000
anyascii/_data/001
anyascii/_data/002
anyascii/_data/003
anyascii/_data/004
anyascii/_data/005
anyascii/_data/006
anyascii/_data/007
anyascii/_data/008
anyascii/_data/009
anyascii/_data/00a
anyascii/_data/00b
anyascii/_data/00c
anyascii/_data/00d
anyascii/_data/00e
anyascii/_data/00f
anyascii/_data/010
anyascii/_data/011
anyascii/_data/012
anyascii/_data/013
anyascii/_data/014
anyascii/_data/015
anyascii/_data/016
anyascii/_data/017
anyascii/_data/018
anyascii/_data/019
anyascii/_data/01a
anyascii/_data/01b
anyascii/_data/01c
anyascii/_data/01d
anyascii/_data/01e
anyascii/_data/01f
anyascii/_data/020
anyascii/_data/021
anyascii/_data/022
anyascii/_data/023
anyascii/_data/024
anyascii/_data/025
anyascii/_data/026
anyascii/_data/027
anyascii/_data/028
anyascii/_data/029
anyascii/_data/02a
anyascii/_data/02b
anyascii/_data/02c
anyascii/_data/02d
anyascii/_data/02e
anyascii/_data/02f
anyascii/_data/030
anyascii/_data/031
anyascii/_data/032
anyascii/_data/033
anyascii/_data/034
anyascii/_data/035
anyascii/_data/036
anyascii/_data/037
anyascii/_data/038
anyascii/_data/039
anyascii/_data/03a
anyascii/_data/03b
anyascii/_data/03c
anyascii/_data/03d
anyascii/_data/03e
anyascii/_data/03f
anyascii/_data/040
anyascii/_data/041
anyascii/_data/042
anyascii/_data/043
anyascii/_data/044
anyascii/_data/045
anyascii/_data/046
anyascii/_data/047
anyascii/_data/048
anyascii/_data/049
anyascii/_data/04a
anyascii/_data/04b
anyascii/_data/04c
anyascii/_data/04d
anyascii/_data/04e
anyascii/_data/04f
anyascii/_data/050
anyascii/_data/051
anyascii/_data/052
anyascii/_data/053
anyascii/_data/054
anyascii/_data/055
anyascii/_data/056
anyascii/_data/057
anyascii/_data/058
anyascii/_data/059
anyascii/_data/05a
anyascii/_data/05b
anyascii/_data/05c
anyascii/_data/05d
anyascii/_data/05e
anyascii/_data/05f
anyascii/_data/060
anyascii/_data/061
anyascii/_data/062
anyascii/_data/063
anyascii/_data/064
anyascii/_data/065
anyascii/_data/066
anyascii/_data/067
anyascii-0.2.0.dist-info/LICENSE
anyascii-0.2.0.dist-info/WHEEL
anyascii-0.2.0.dist-info/METADATA
anyascii-0.2.0.dist-info/RECORD
