Metadata-Version: 1.1
Name: anyascii
Version: 0.2.0
Summary: Unicode to ASCII transliteration
Home-page: https://github.com/anyascii/anyascii
Author: Hunter WB
Author-email: hunter@hunterwb.com
